_rinterface_cffi_abi.py
_rinterface_cffi_api.pyd
rpy2/rinterface/__init__.py
rpy2/rinterface/py.typed
rpy2/rinterface/tests/__init__.py
rpy2/rinterface/tests/test_bufferprotocol.py
rpy2/rinterface/tests/test_callbacks.py
rpy2/rinterface/tests/test_conversion.py
rpy2/rinterface/tests/test_embedded_r.py
rpy2/rinterface/tests/test_endr.py
rpy2/rinterface/tests/test_environment.py
rpy2/rinterface/tests/test_externalptr.py
rpy2/rinterface/tests/test_functions.py
rpy2/rinterface/tests/test_memorymanagement.py
rpy2/rinterface/tests/test_na.py
rpy2/rinterface/tests/test_noinitialization.py
rpy2/rinterface/tests/test_openrlib.py
rpy2/rinterface/tests/test_sexp.py
rpy2/rinterface/tests/test_symbol.py
rpy2/rinterface/tests/test_threading.py
rpy2/rinterface/tests/test_vector_bool.py
rpy2/rinterface/tests/test_vector_byte.py
rpy2/rinterface/tests/test_vector_complex.py
rpy2/rinterface/tests/test_vector_float.py
rpy2/rinterface/tests/test_vector_int.py
rpy2/rinterface/tests/test_vector_lang.py
rpy2/rinterface/tests/test_vector_list.py
rpy2/rinterface/tests/test_vector_numpy.py
rpy2/rinterface/tests/test_vector_pairlist.py
rpy2/rinterface/tests/test_vector_str.py
rpy2/rinterface/tests/test_vectors.py
rpy2/rinterface/tests/utils.py
rpy2/rinterface/tests/rlike/test_container.py
rpy2/rinterface/tests/rlike/test_functional.py
rpy2/rinterface/tests/rlike/test_indexing.py
rpy2/rinterface_lib/RPY2.h
rpy2/rinterface_lib/R_API.h
rpy2/rinterface_lib/R_API_eventloop.c
rpy2/rinterface_lib/R_API_eventloop.h
rpy2/rinterface_lib/__init__.py
rpy2/rinterface_lib/_bufferprotocol.c
rpy2/rinterface_lib/_bufferprotocol.cp311-win_amd64.pyd
rpy2/rinterface_lib/_rinterface_capi.py
rpy2/rinterface_lib/_rinterface_cffi_build.py
rpy2/rinterface_lib/bufferprotocol.py
rpy2/rinterface_lib/callbacks.py
rpy2/rinterface_lib/conversion.py
rpy2/rinterface_lib/embedded.py
rpy2/rinterface_lib/ffi_proxy.py
rpy2/rinterface_lib/memorymanagement.py
rpy2/rinterface_lib/na_values.py
rpy2/rinterface_lib/openrlib.py
rpy2_rinterface-3.6.3.dist-info/METADATA
rpy2_rinterface-3.6.3.dist-info/WHEEL
rpy2_rinterface-3.6.3.dist-info/top_level.txt
rpy2_rinterface-3.6.3.dist-info/RECORD
